LICENSE
README.md
setup.py
EcoSim.egg-info/PKG-INFO
EcoSim.egg-info/SOURCES.txt
EcoSim.egg-info/dependency_links.txt
EcoSim.egg-info/requires.txt
EcoSim.egg-info/top_level.txt
ecosim/__init__.py
ecosim/climate.py
ecosim/ecosystem.py
ecosim/plants.py
ecosim/population.py
ecosim/utils.py
tests/test.py