Metadata-Version: 2.1
Name: EcoSim
Version: 0.0.1
Summary: A library for ecological systems modeling and simulations
Home-page: https://github.com/FlacSy/EcoSim
Author: FlacSy
Author-email: flacsy.tw@gmail.com
License-File: LICENSE
Requires-Dist: numpy
Requires-Dist: scipy
Requires-Dist: matplotlib
